oaktis/__init__.py
oaktis/client.py
oaktis/types.py
oaktis-0.1.11.dist-info/METADATA
oaktis-0.1.11.dist-info/WHEEL
oaktis-0.1.11.dist-info/RECORD
