Metadata-Version: 2.4
Name: oaktis
Version: 0.1.11
Summary: Official Python SDK for Oaktis - AI-powered image & video generation
Project-URL: Homepage, https://oaktis.com/?utm_source=pypi&utm_medium=devhub&utm_campaign=oss-sdk&utm_content=pkg-homepage
Project-URL: Documentation, https://docs.oaktis.com
Project-URL: Repository, https://github.com/Oaktis/Oaktis
Project-URL: Issues, https://github.com/Oaktis/Oaktis/issues
Author-email: Oaktis <dev@oaktis.com>
License: MIT
Keywords: ai,api,generation,image,oaktis,video
Classifier: Development Status :: 4 - Beta
Classifier: Intended Audience :: Developers
Classifier: License :: OSI Approved :: MIT License
Classifier: Programming Language :: Python :: 3
Classifier: Programming Language :: Python :: 3.9
Classifier: Programming Language :: Python :: 3.10
Classifier: Programming Language :: Python :: 3.11
Classifier: Programming Language :: Python :: 3.12
Classifier: Topic :: Software Development :: Libraries :: Python Modules
Requires-Python: >=3.9
Requires-Dist: httpx>=0.25.0
Requires-Dist: pydantic>=2.5.0
Provides-Extra: dev
Requires-Dist: black>=23.0.0; extra == 'dev'
Requires-Dist: mypy>=1.7.0; extra == 'dev'
Requires-Dist: pytest-asyncio>=0.21.0; extra == 'dev'
Requires-Dist: pytest>=7.4.0; extra == 'dev'
Requires-Dist: ruff>=0.1.0; extra == 'dev'
